Workbook

Sheet Transactions
A1: transaction_id | B1: transaction_date | C1: customer_id | D1: department | E1: product_sku | F1: product_name | G1: quantity | H1: unit_price | I1: discount_pct | J1: total_cost | K1: payment_method | L1: sales_channel | M1: register_id
A2: 101047 | B2: 45290 | C2: 47786 | D2: Electronics | E2: EL-102 | F2: Bluetooth Headphones | G2: 2 | H2: 79.99 | J2: 159.98 | K2: Credit Card | L2: In-Store | M2: REG-12
A3: 101291 | B3: 45160 | C3: 83378 | D3: PHARMACY | E3: PH-001 | F3: Ibuprofen 200ct | G3: 5 | H3: 9.99 | J3: 49.95 | K3: Cash | L3: Curbside Pickup | M3: REG-19
A4: 101812 | B4: 44683 | C4: 60430 | D4: Furniture | E4: FU-001 | F4: Folding Chair | G4: 1 | H4: 29.74 | I4: 0.15 | J4: 25.28 | K4: Credit Card | L4: In-Store | M4: REG-6
A5: 102088 | B5: 45078 | C5: 80498 | D5: Toys | E5: TY-203 | F5: Nerf Gun | G5: 5 | H5: 24.99 | J5: 124.95 | K5: EBT | L5: In-Store | M5: REG-14
A6: 102306 | B6: 44998 | C6: 62555 | D6: Electronics | E6: EL-303 | F6: USB-C Hub | G6: 3 | H6: 34.99 | J6: 104.97 | K6: Debit Card | L6: Online | M6: REG-12
A7: 102465 | B7: 44900 | C7: 78782 | D7: Toys | E7: TY-304 | F7: Board Game | G7: 5 | H7: 20.99 | I7: 0.3 | J7: 73.46 | K7: EBT | L7: In-Store | M7: REG-14
A8: 102502 | B8: 44868 | D8: Pharmacy | E8: PH-304 | F8: Bandage Assortment | G8: 2 | H8: 4.49 | I8: 0.25 | J8: 6.74 | K8: Cash | L8: In-Store | M8: REG-15
A9: 102533 | B9: 45555 | D9: Grocery | E9: GR-007 | F9: Pasta 1lb | G9: 1 | H9: 1.34 | I9: 0.25 | J9: 1.01 | K9: Credit Card | L9: In-Store | M9: REG-11
A10: 103055 | B10: 45048 | C10: 95915 | D10: Beauty | E10: BE-203 | F10: Mascara | G10: 2 | H10: 8.99 | J10: 17.98 | K10: Debit Card | L10: Online | M10: REG-11
A11: 103292 | B11: 45196 | C11: 46193 | D11: Furniture | E11: FU-203 | F11: Desk Lamp | G11: 1 | H11: 19.59 | I11: 0.3 | J11: 13.71 | K11: Gift Card | L11: Online | M11: REG-16
A12: 103300 | B12: 45486 | C12: 19709 | D12: Electronics | E12: EL-707 | F12: Tablet 10" | G12: 3 | H12: 230.99 | I12: 0.3 | J12: 485.08 | K12: Debit Card | L12: Online | M12: REG-13
A13: 103496 | B13: 45395 | C13: 42392 | D13: Pharmacy | E13: PH-405 | F13: Hand Sanitizer 8oz | G13: 1 | H13: 3.39 | I13: 0.15 | J13: 2.88 | K13: Debit Card | L13: In-Store | M13: REG-6
A14: 103506 | B14: 45367 | C14: 91356 | D14: Furniture | E14: FU-304 | F14: Storage Ottoman | G14: 5 | H14: 52.24 | I14: 0.05 | J14: 248.14 | K14: Credit Card | L14: In-Store | M14: REG-18
A15: 103735 | B15: 44600 | D15: Grocery | E15: GR-007 | F15: Pasta 1lb | G15: 2 | H15: 1.79 | J15: 3.58 | K15: Credit Card | L15: In-Store | M15: REG-12
A16: 104478 | B16: 45165 | C16: 86184 | D16: Automotive | E16: AU-203 | F16: Windshield Washer Fluid | G16: 1 | H16: 4.99 | J16: 4.99 | K16: Check | L16: In-Store | M16: REG-1
A17: 104488 | B17: 44889 | C17: 47751 | D17: Automotive | E17: AU-203 | F17: Windshield Washer Fluid | G17: 3 | H17: 4.74 | I17: 0.05 | J17: 13.51 | K17: Debit Card | L17: Online | M17: REG-12
A18: 104523 | B18: 45319 | C18: 10364 | D18: Automotive | E18: AU-001 | F18: Motor Oil 5qt | G18: 2 | H18: 19.99 | I18: 0.2 | J18: 31.98 | K18: Credit Card | L18: Online | M18: REG-16
A19: 104855 | B19: 45547 | C19: 48062 | D19: Furniture | E19: FU-102 | F19: Bookshelf 5-Tier | G19: 2 | H19: 89.99 | J19: 179.98 | K19: Debit Card | L19: In-Store | M19: REG-6
A20: 105337 | B20: 44814 | C20: 42955 | D20: Electronics | E20: EL-303 | F20: USB-C Hub | G20: 2 | H20: 34.99 | J20: 69.98 | K20: Credit Card | L20: Online | M20: REG-13
A21: 105411 | B21: 44805 | C21: 73284 | D21: Toys | E21: TY-506 | F21: RC Car | G21: 1 | H21: 33.99 | I21: 0.15 | J21: 28.89 | K21: Debit Card | L21: Online | M21: REG-15
A22: 105767 | B22: 44604 | C22: 15863 | D22: Grocery | E22: GR-002 | F22: White Bread | G22: 3 | H22: 2.09 | I22: 0.3 | J22: 4.39 | K22: Gift Card | L22: In-Store | M22: REG-20
A23: 105891 | B23: 45425 | C23: 64264 | D23: Electronics | E23: TV-001 | F23: 4K Smart TV 55" | G23: 1 | H23: 499.99 | J23: 499.99 | K23: Debit Card | L23: Curbside Pickup | M23: REG-19
A24: 105898 | B24: 45614 | D24: Electronics | E24: EL-606 | F24: Smart Speaker | G24: 3 | H24: 89.99 | J24: 269.97 | K24: Credit Card | L24: In-Store | M24: REG-7
A25: 105910 | B25: 45026 | C25: 73703 | D25: Sports | E25: SP-203 | F25: Water Bottle 32oz | G25: 3 | H25: 11.89 | I25: 0.3 | J25: 24.97 | K25: Debit Card | L25: In-Store | M25: REG-16
A26: 105960 | B26: 45338 | C26: 70702 | D26: Home & Garden | E26: HG-203 | F26: Scented Candle | G26: 1 | H26: 9.09 | I26: 0.3 | J26: 6.36 | K26: Cash | L26: In-Store | M26: REG-15
A27: 106029 | B27: 45581 | C27: 96438 | D27: Toys | E27: TY-001 | F27: LEGO City Set | G27: 2 | H27: 37.49 | I27: 0.25 | J27: 56.24 | K27: Credit Card | L27: In-Store | M27: REG-10
A28: 106047 | B28: 44876 | C28: 81600 | D28: Grocery | E28: GR-006 | F28: Greek Yogurt 32oz | G28: 1 | H28: 4.72 | J28: 4.72 | K28: Cash | L28: In-Store | M28: REG-7
A29: 106263 | B29: 44902 | C29: 95178 | D29: Grocery | E29: GR-008 | F29: Canned Tomatoes | G29: 5 | H29: 0.9 | I29: 0.3 | J29: 3.15 | K29: Mobile Pay | L29: In-Store | M29: REG-14
A30: 106543 | B30: 45204 | C30: 88674 | D30: Automotive | E30: AU-203 | F30: Windshield Washer Fluid | G30: 1 | H30: 3.99 | I30: 0.2 | J30: 3.19 | K30: Debit Card | L30: In-Store | M30: REG-9
A31: 106587 | B31: 45594 | C31: 94688 | D31: Clothing | E31: CL-506 | F31: Yoga Pants | G31: 4 | H31: 27.99 | J31: 111.96 | K31: Credit Card | L31: In-Store | M31: REG-1
A32: 106747 | B32: 45229 | C32: 22687 | D32: Automotive | E32: AU-001 | F32: Motor Oil 5qt | G32: 2 | H32: 19.99 | I32: 0.2 | J32: 31.98 | K32: Cash | L32: Online | M32: REG-20
A33: 106802 | B33: 45075 | C33: 54297 | D33: Toys | E33: TY-304 | F33: Board Game | G33: 1 | H33: 28.49 | I33: 0.05 | J33: 27.07 | K33: Credit Card | L33: Online | M33: REG-10
A34: 106949 | B34: 45526 | C34: 77873 | D34: Sports | E34: SP-001 | F34: Yoga Mat | G34: 2 | H34: 22.99 | J34: 45.98 | K34: Check | L34: Online | M34: REG-8
A35: 106959 | B35: 45625 | C35: 17057 | D35: PHARMACY | E35: PH-405 | F35: Hand Sanitizer 8oz | G35: 2 | H35: 3.39 | I35: 0.15 | J35: 5.76 | K35: EBT | L35: Online | M35: REG-17
A36: 107239 | B36: 44834 | C36: 29478 | D36: Grocery | E36: GR-002 | F36: White Bread | G36: 1 | H36: 2.09 | I36: 0.3 | J36: 1.46 | K36: Cash | L36: In-Store | M36: REG-6
A37: 107432 | B37: 44917 | C37: 24560 | D37: Electronics | E37: EL-505 | F37: Wireless Charger | G37: 5 | H37: 23.99 | I37: 0.2 | J37: 95.96 | K37: Mobile Pay | L37: In-Store | M37: REG-1
A38: 107461 | B38: 45309 | C38: 64862 | D38: GROCERY | E38: GR-010 | F38: Eggs 12ct | G38: 1 | H38: 3.49 | J38: 3.49 | K38: Debit Card | L38: In-Store | M38: REG-10
A39: 107567 | B39: 44771 | C39: 84944 | D39: Beauty | E39: BE-001 | F39: Shampoo 16oz | G39: 5 | H39: 6.99 | J39: 34.95 | K39: Debit Card | L39: In-Store | M39: REG-7
A40: 107786 | B40: 45135 | C40: 68036 | D40: Automotive | E40: AU-304 | F40: Car Phone Mount | G40: 1 | H40: 11.24 | I40: 0.25 | J40: 8.43 | K40: Cash | L40: In-Store | M40: REG-18
A41: 108023 | B41: 44733 | C41: 34612 | D41: Furniture | E41: FU-405 | F41: TV Stand | G41: 1 | H41: 107.99 | I41: 0.1 | J41: 97.19 | K41: Credit Card | L41: In-Store
A42: 108027 | B42: 45648 | C42: 97150 | D42: PHARMACY | E42: PH-102 | F42: Vitamin D 100ct | G42: 5 | H42: 12.99 | J42: 64.95 | K42: Credit Card | L42: In-Store | M42: REG-3
A43: 108286 | B43: 45185 | C43: 29249 | D43: Beauty | E43: BE-304 | F43: Lip Balm 3pk | G43: 5 | H43: 4.24 | I43: 0.15 | J43: 18.02 | K43: Debit Card | L43: Curbside Pickup | M43: REG-5
A44: 108304 | B44: 44607 | C44: 50153 | D44: Sports | E44: SP-203 | F44: Water Bottle 32oz | G44: 3 | H44: 11.89 | I44: 0.3 | J44: 24.97 | K44: Mobile Pay | L44: Curbside Pickup | M44: REG-19
A45: 108351 | B45: 45303 | C45: 67610 | D45: Clothing | E45: CL-102 | F45: Women's T-Shirt | G45: 2 | H45: 9.74 | I45: 0.25 | J45: 14.61 | K45: Debit Card | L45: In-Store | M45: REG-16
A46: 108680 | B46: 44674 | C46: 41537 | D46: Electronics | E46: EL-303 | F46: USB-C Hub | G46: 1 | H46: 26.24 | I46: 0.25 | J46: 19.68 | K46: Credit Card | L46: In-Store | M46: REG-10
A47: 108817 | B47: 45173 | C47: 98245 | D47: Toys | E47: TY-506 | F47: RC Car | G47: 1 | H47: 31.99 | I47: 0.2 | J47: 25.59 | K47: Debit Card | L47: Online | M47: REG-2
A48: 108830 | B48: 45571 | C48: 95476 | D48: Electronics | E48: EL-303 | F48: USB-C Hub | G48: 5 | H48: 34.99 | J48: 174.95 | K48: Debit Card | L48: In-Store | M48: REG-10
A49: 109127 | B49: 45504 | C49: 25217 | D49: Furniture | E49: FU-001 | F49: Folding Chair | G49: 1 | H49: 26.24 | I49: 0.25 | J49: 19.68 | K49: Cash | L49: In-Store | M49: REG-19
A50: 109269 | B50: 45600 | C50: 36699 | D50: Automotive | E50: AU-203 | F50: Windshield Washer Fluid | G50: 1 | H50: 3.74 | I50: 0.25 | J50: 2.8 | K50: Gift Card | L50: In-Store | M50: REG-8
A51: 109525 | B51: 45351 | C51: 71899 | D51: Electronics | E51: EL-303 | F51: USB-C Hub | G51: 5 | H51: 27.99 | I51: 0.2 | J51: 111.96 | K51: Cash | L51: In-Store | M51: REG-6
A52: 109596 | B52: 45083 | C52: 12461 | D52: AUTOMOTIVE | E52: AU-405 | F52: Jumper Cables | G52: 1 | H52: 20.99 | I52: 0.3 | J52: 14.69 | K52: Debit Card | L52: Online | M52: REG-9
A53: 109883 | B53: 45634 | C53: 54659 | D53: Toys | E53: TY-506 | F53: RC Car | G53: 4 | H53: 33.99 | I53: 0.15 | J53: 115.57 | K53: Mobile Pay | L53: In-Store | M53: REG-14
A54: 110228 | B54: 44683 | C54: 48942 | D54: Automotive | E54: AU-203 | F54: Windshield Washer Fluid | G54: 5 | H54: 4.99 | J54: 24.95 | K54: Credit Card | L54: In-Store | M54: REG-2
A55: 110444 | B55: 45383 | C55: 71400 | D55: Electronics | E55: EL-201 | F55: iPhone Case | G55: 1 | H55: 19.99 | J55: 19.99 | K55: Credit Card | L55: In-Store | M55: REG-7
A56: 110506 | B56: 45268 | C56: 35067 | D56: Home & Garden | E56: HG-001 | F56: Potting Soil 20qt | G56: 1 | H56: 8.99 | J56: 8.99 | K56: Credit Card | L56: In-Store | M56: REG-17
A57: 110649 | B57: 45296 | C57: 87204 | D57: Electronics | E57: TV-001 | F57: 4K Smart TV 55" | G57: 1 | H57: 374.99 | I57: 0.25 | J57: 281.24 | K57: Mobile Pay | L57: In-Store | M57: REG-10
A58: 110666 | B58: 45167 | D58: Automotive | E58: AU-102 | F58: Car Air Freshener | G58: 2 | H58: 3.49 | J58: 6.98 | K58: Cash | L58: In-Store | M58: REG-2
A59: 110743 | B59: 44901 | C59: 16675 | D59: Beauty | E59: BE-304 | F59: Lip Balm 3pk | G59: 1 | H59: 4.24 | I59: 0.15 | J59: 3.6 | K59: Cash | L59: In-Store | M59: REG-18
A60: 111256 | B60: 44659 | C60: 15018 | D60: Grocery | E60: GR-004 | F60: Bagged Salad Mix | G60: 1 | H60: 3.79 | J60: 3.79 | K60: Credit Card | L60: In-Store | M60: REG-18
A61: 111480 | B61: 44578 | D61: Clothing | E61: CL-607 | F61: Dress Socks 6pk | G61: 2 | H61: 6.99 | I61: 0.3 | J61: 9.79 | K61: Debit Card | L61: In-Store | M61: REG-6
A62: 111503 | B62: 45305 | C62: 66196 | D62: Pharmacy | E62: PH-102 | F62: Vitamin D 100ct | G62: 1 | H62: 9.74 | I62: 0.25 | J62: 7.3 | K62: Credit Card | L62: In-Store | M62: REG-5
A63: 111807 | B63: 44618 | D63: Home & Garden | E63: HG-304 | F63: Picture Frame 8x10 | G63: 2 | H63: 6.79 | I63: 0.15 | J63: 11.54 | K63: Cash | L63: In-Store | M63: REG-13
A64: 111972 | B64: 45387 | C64: 67694 | D64: Beauty | E64: BE-405 | F64: Body Lotion 16oz | G64: 2 | H64: 7.99 | J64: 15.98 | K64: Credit Card | L64: In-Store | M64: REG-15
A65: 112088 | B65: 45103 | C65: 39411 | D65: Clothing | E65: CL-203 | F65: Kids Hoodie | G65: 3 | H65: 16.09 | I65: 0.3 | J65: 33.79 | K65: Cash | L65: In-Store
A66: 112439 | B66: 44859 | C66: 51377 | D66: Beauty | E66: BE-304 | F66: Lip Balm 3pk | G66: 4 | H66: 3.49 | I66: 0.3 | J66: 9.77 | K66: Debit Card | L66: Online | M66: REG-19
A67: 112458 | B67: 45057 | C67: 15965 | D67: Toys | E67: TY-506 | F67: RC Car | G67: 4 | H67: 39.99 | J67: 159.96 | K67: EBT | L67: In-Store | M67: REG-10
A68: 112714 | B68: 44744 | C68: 43443 | D68: Automotive | E68: AU-001 | F68: Motor Oil 5qt | G68: 1 | H68: 24.99 | J68: 24.99 | K68: Credit Card | L68: In-Store | M68: REG-19
A69: 112715 | B69: 45578 | C69: 44039 | D69: Beauty | E69: BE-102 | F69: Face Moisturizer | G69: 1 | H69: 14.99 | J69: 14.99 | K69: Check | L69: Curbside Pickup | M69: REG-16
A70: 112778 | B70: 45543 | C70: 34879 | D70: Home & Garden | E70: HG-405 | F70: Storage Bins 3pk | G70: 2 | H70: 13.59 | I70: 0.2 | J70: 21.74 | K70: Gift Card | L70: Online | M70: REG-7
A71: 112940 | B71: 44752 | C71: 83339 | D71: Clothing | E71: CL-506 | F71: Yoga Pants | G71: 4 | H71: 23.79 | I71: 0.15 | J71: 80.89 | K71: Credit Card | L71: In-Store | M71: REG-16
A72: 113121 | B72: 45431 | C72: 86078 | D72: Electronics | E72: EL-102 | F72: Bluetooth Headphones | G72: 1 | H72: 79.99 | J72: 79.99 | K72: Credit Card | L72: Online | M72: REG-15
A73: 113173 | B73: 45253 | C73: 29832 | D73: Sports | E73: SP-304 | F73: Resistance Bands | G73: 2 | H73: 9.74 | I73: 0.25 | J73: 14.61 | K73: Debit Card | L73: In-Store | M73: REG-20
A74: 113177 | B74: 45358 | C74: 29893 | D74: Furniture | E74: FU-203 | F74: Desk Lamp | G74: 5 | H74: 20.99 | I74: 0.25 | J74: 78.71 | K74: EBT | L74: In-Store | M74: REG-11
A75: 113499 | B75: 44699 | D75: Furniture | E75: FU-203 | F75: Desk Lamp | G75: 3 | H75: 27.99 | J75: 83.97 | K75: Credit Card | L75: Curbside Pickup
A76: 113522 | B76: 44773 | C76: 53050 | D76: Toys | E76: TY-506 | F76: RC Car | G76: 1 | H76: 39.99 | J76: 39.99 | K76: Gift Card | L76: In-Store | M76: REG-3
A77: 113765 | B77: 44715 | C77: 73916 | D77: Home & Garden | E77: HG-506 | F77: Throw Pillow | G77: 1 | H77: 14.99 | I77: 0.25 | J77: 11.24 | K77: Debit Card | L77: In-Store | M77: REG-17
A78: 114210 | B78: 45348 | C78: 42550 | D78: Electronics | E78: EL-102 | F78: Bluetooth Headphones | G78: 1 | H78: 79.99 | J78: 79.99 | K78: Credit Card | L78: In-Store | M78: REG-11
A79: 114270 | B79: 45331 | D79: Grocery | E79: GR-004 | F79: Bagged Salad Mix | G79: 1 | H79: 3.79 | J79: 3.79 | K79: Cash | L79: In-Store | M79: REG-5
A80: 114717 | B80: 44835 | C80: 82298 | D80: Clothing | E80: CL-001 | F80: Men's Jeans | G80: 4 | H80: 33.24 | I80: 0.05 | J80: 126.31 | K80: Gift Card | L80: Curbside Pickup | M80: REG-13
A81: 114743 | B81: 45627 | C81: 96886 | D81: Toys | E81: TY-203 | F81: Nerf Gun | G81: 2 | H81: 23.74 | I81: 0.05 | J81: 45.11 | K81: Credit Card | L81: In-Store | M81: REG-1
A82: 114834 | B82: 44953 | C82: 17772 | D82: Home & Garden | E82: HG-102 | F82: Garden Hose 50ft | G82: 4 | H82: 26.99 | I82: 0.1 | J82: 97.16 | K82: Mobile Pay | L82: In-Store | M82: REG-19
A83: 114868 | B83: 45348 | C83: 93946 | D83: Electronics | E83: EL-707 | F83: Tablet 10" | G83: 1 | H83: 329.99 | J83: 329.99 | K83: Credit Card | L83: In-Store | M83: REG-18
A84: 114930 | B84: 44854 | C84: 42668 | D84: Home & Garden | E84: HG-405 | F84: Storage Bins 3pk | G84: 1 | H84: 16.99 | J84: 16.99 | K84: Credit Card | L84: Online | M84: REG-8
A85: 115017 | B85: 44660 | C85: 31218 | D85: Electronics | E85: EL-606 | F85: Smart Speaker | G85: 5 | H85: 85.49 | I85: 0.05 | J85: 406.08 | K85: Cash | L85: In-Store | M85: REG-9
A86: 115166 | B86: 44810 | C86: 31680 | D86: Furniture | E86: FU-304 | F86: Storage Ottoman | G86: 1 | H86: 52.24 | I86: 0.05 | J86: 49.63 | K86: Credit Card | L86: Online | M86: REG-12
A87: 115330 | B87: 44615 | C87: 74764 | D87: Furniture | E87: FU-102 | F87: Bookshelf 5-Tier | G87: 1 | H87: 67.49 | I87: 0.25 | J87: 50.62 | K87: Debit Card | L87: In-Store | M87: REG-8
A88: 115577 | B88: 44714 | C88: 33437 | D88: Sports | E88: SP-506 | F88: Foam Roller | G88: 1 | H88: 15.99 | I88: 0.2 | J88: 12.79 | K88: Debit Card | L88: In-Store | M88: REG-9
A89: 115659 | B89: 45396 | C89: 85378 | D89: Home & Garden | E89: HG-607 | F89: Laundry Detergent | G89: 1 | H89: 13.49 | J89: 13.49 | K89: Cash | L89: In-Store | M89: REG-19
A90: 115664 | B90: 45637 | C90: 18693 | D90: Electronics | E90: EL-808 | F90: Gaming Controller | G90: 1 | H90: 59.99 | J90: 59.99 | K90: Debit Card | L90: In-Store | M90: REG-4
A91: 115775 | B91: 45523 | C91: 65009 | D91: Furniture | E91: FU-203 | F91: Desk Lamp | G91: 2 | H91: 27.99 | J91: 55.98 | K91: Credit Card | L91: In-Store | M91: REG-16
A92: 116223 | B92: 44615 | C92: 59799 | D92: Sports | E92: SP-203 | F92: Water Bottle 32oz | G92: 2 | H92: 16.99 | J92: 33.98 | K92: Cash | L92: In-Store | M92: REG-17
A93: 116229 | B93: 45014 | C93: 55816 | D93: Grocery | E93: GR-009 | F93: Frozen Pizza | G93: 1 | H93: 6.79 | I93: 0.15 | J93: 5.77 | K93: Credit Card | L93: In-Store | M93: REG-16
A94: 117389 | B94: 45493 | C94: 13384 | D94: Clothing | E94: CL-506 | F94: Yoga Pants | G94: 4 | H94: 25.19 | I94: 0.1 | J94: 90.68 | K94: Gift Card | L94: Curbside Pickup | M94: REG-15
A95: 117444 | B95: 45580 | C95: 61221 | D95: Automotive | E95: AU-203 | F95: Windshield Washer Fluid | G95: 3 | H95: 4.99 | J95: 14.97 | K95: Credit Card | L95: Online | M95: REG-14
A96: 117452 | B96: 44756 | C96: 73624 | D96: Home & Garden | E96: HG-607 | F96: Laundry Detergent | G96: 3 | H96: 9.44 | I96: 0.3 | J96: 19.82 | K96: Credit Card | L96: Online | M96: REG-14
A97: 117463 | B97: 45267 | D97: Home & Garden | E97: HG-607 | F97: Laundry Detergent | G97: 1 | H97: 12.82 | I97: 0.05 | J97: 12.18 | K97: Check | L97: In-Store | M97: REG-17
A98: 117526 | B98: 44684 | C98: 72147 | D98: Furniture | E98: FU-001 | F98: Folding Chair | G98: 4 | H98: 34.99 | J98: 139.96 | K98: Debit Card | L98: In-Store | M98: REG-16
A99: 117538 | B99: 45651 | C99: 12246 | D99: Pharmacy | E99: PH-001 | F99: Ibuprofen 200ct | G99: 2 | H99: 6.99 | I99: 0.3 | J99: 9.79 | K99: Mobile Pay | L99: In-Store | M99: REG-8
A100: 117658 | B100: 44969 | C100: 62952 | D100: Automotive | E100: AU-405 | F100: Jumper Cables | G100: 3 | H100: 29.99 | J100: 89.97 | K100: Credit Card | L100: In-Store | M100: REG-7
...

Sheet Transactions (Cleaned)
A1: transaction_id | B1: transaction_date | C1: customer_id | D1: department | E1: product_sku | F1: product_name | G1: quantity | H1: unit_price | I1: discount_pct | J1: total_cost | K1: payment_method | L1: sales_channel | M1: register_id
A2: 101047 | B2: 45290 | C2: 47786 | D2: =PROPER(Transactions!D2) -> Electronics | E2: EL-102 | F2: Bluetooth Headphones | G2: 2 | H2: 79.99 | I2: =IF(Transactions!I2="",0,Transactions!I2) -> 0 | J2: =(H2*G2)*(1-I2) -> 159.98 | K2: Credit Card | L2: In-Store | M2: =REPLACE(Transactions!M2,1,4,"") -> 12
A3: 101291 | B3: 45160 | C3: 83378 | D3: =PROPER(Transactions!D3) -> Pharmacy | E3: PH-001 | F3: Ibuprofen 200ct | G3: 5 | H3: 9.99 | I3: =IF(Transactions!I3="",0,Transactions!I3) -> 0 | J3: =(H3*G3)*(1-I3) -> 49.95 | K3: Cash | L3: Curbside Pickup | M3: =REPLACE(Transactions!M3,1,4,"") -> 19
A4: 101812 | B4: 44683 | C4: 60430 | D4: =PROPER(Transactions!D4) -> Furniture | E4: FU-001 | F4: Folding Chair | G4: 1 | H4: 29.74 | I4: =IF(Transactions!I4="",0,Transactions!I4) -> 0.15 | J4: =(H4*G4)*(1-I4) -> 25.279 | K4: Credit Card | L4: In-Store | M4: =REPLACE(Transactions!M4,1,4,"") -> 6
A5: 102088 | B5: 45078 | C5: 80498 | D5: =PROPER(Transactions!D5) -> Toys | E5: TY-203 | F5: Nerf Gun | G5: 5 | H5: 24.99 | I5: =IF(Transactions!I5="",0,Transactions!I5) -> 0 | J5: =(H5*G5)*(1-I5) -> 124.95 | K5: EBT | L5: In-Store | M5: =REPLACE(Transactions!M5,1,4,"") -> 14
A6: 102306 | B6: 44998 | C6: 62555 | D6: =PROPER(Transactions!D6) -> Electronics | E6: EL-303 | F6: USB-C Hub | G6: 3 | H6: 34.99 | I6: =IF(Transactions!I6="",0,Transactions!I6) -> 0 | J6: =(H6*G6)*(1-I6) -> 104.97 | K6: Debit Card | L6: Online | M6: =REPLACE(Transactions!M6,1,4,"") -> 12
A7: 102465 | B7: 44900 | C7: 78782 | D7: =PROPER(Transactions!D7) -> Toys | E7: TY-304 | F7: Board Game | G7: 5 | H7: 20.99 | I7: =IF(Transactions!I7="",0,Transactions!I7) -> 0.3 | J7: =(H7*G7)*(1-I7) -> 73.465 | K7: EBT | L7: In-Store | M7: =REPLACE(Transactions!M7,1,4,"") -> 14
A8: 102502 | B8: 44868 | D8: =PROPER(Transactions!D8) -> Pharmacy | E8: PH-304 | F8: Bandage Assortment | G8: 2 | H8: 4.49 | I8: =IF(Transactions!I8="",0,Transactions!I8) -> 0.25 | J8: =(H8*G8)*(1-I8) -> 6.735 | K8: Cash | L8: In-Store | M8: =REPLACE(Transactions!M8,1,4,"") -> 15
A9: 102533 | B9: 45555 | D9: =PROPER(Transactions!D9) -> Grocery | E9: GR-007 | F9: Pasta 1lb | G9: 1 | H9: 1.34 | I9: =IF(Transactions!I9="",0,Transactions!I9) -> 0.25 | J9: =(H9*G9)*(1-I9) -> 1.005 | K9: Credit Card | L9: In-Store | M9: =REPLACE(Transactions!M9,1,4,"") -> 11
A10: 103055 | B10: 45048 | C10: 95915 | D10: =PROPER(Transactions!D10) -> Beauty | E10: BE-203 | F10: Mascara | G10: 2 | H10: 8.99 | I10: =IF(Transactions!I10="",0,Transactions!I10) -> 0 | J10: =(H10*G10)*(1-I10) -> 17.98 | K10: Debit Card | L10: Online | M10: =REPLACE(Transactions!M10,1,4,"") -> 11
A11: 103292 | B11: 45196 | C11: 46193 | D11: =PROPER(Transactions!D11) -> Furniture | E11: FU-203 | F11: Desk Lamp | G11: 1 | H11: 19.59 | I11: =IF(Transactions!I11="",0,Transactions!I11) -> 0.3 | J11: =(H11*G11)*(1-I11) -> 13.713 | K11: Gift Card | L11: Online | M11: =REPLACE(Transactions!M11,1,4,"") -> 16
A12: 103300 | B12: 45486 | C12: 19709 | D12: =PROPER(Transactions!D12) -> Electronics | E12: EL-707 | F12: Tablet 10" | G12: 3 | H12: 230.99 | I12: =IF(Transactions!I12="",0,Transactions!I12) -> 0.3 | J12: =(H12*G12)*(1-I12) -> 485.079 | K12: Debit Card | L12: Online | M12: =REPLACE(Transactions!M12,1,4,"") -> 13
A13: 103496 | B13: 45395 | C13: 42392 | D13: =PROPER(Transactions!D13) -> Pharmacy | E13: PH-405 | F13: Hand Sanitizer 8oz | G13: 1 | H13: 3.39 | I13: =IF(Transactions!I13="",0,Transactions!I13) -> 0.15 | J13: =(H13*G13)*(1-I13) -> 2.8815 | K13: Debit Card | L13: In-Store | M13: =REPLACE(Transactions!M13,1,4,"") -> 6
A14: 103506 | B14: 45367 | C14: 91356 | D14: =PROPER(Transactions!D14) -> Furniture | E14: FU-304 | F14: Storage Ottoman | G14: 5 | H14: 52.24 | I14: =IF(Transactions!I14="",0,Transactions!I14) -> 0.05 | J14: =(H14*G14)*(1-I14) -> 248.14 | K14: Credit Card | L14: In-Store | M14: =REPLACE(Transactions!M14,1,4,"") -> 18
A15: 103735 | B15: 44600 | D15: =PROPER(Transactions!D15) -> Grocery | E15: GR-007 | F15: Pasta 1lb | G15: 2 | H15: 1.79 | I15: =IF(Transactions!I15="",0,Transactions!I15) -> 0 | J15: =(H15*G15)*(1-I15) -> 3.58 | K15: Credit Card | L15: In-Store | M15: =REPLACE(Transactions!M15,1,4,"") -> 12
A16: 104478 | B16: 45165 | C16: 86184 | D16: =PROPER(Transactions!D16) -> Automotive | E16: AU-203 | F16: Windshield Washer Fluid | G16: 1 | H16: 4.99 | I16: =IF(Transactions!I16="",0,Transactions!I16) -> 0 | J16: =(H16*G16)*(1-I16) -> 4.99 | K16: Check | L16: In-Store | M16: =REPLACE(Transactions!M16,1,4,"") -> 1
A17: 104488 | B17: 44889 | C17: 47751 | D17: =PROPER(Transactions!D17) -> Automotive | E17: AU-203 | F17: Windshield Washer Fluid | G17: 3 | H17: 4.74 | I17: =IF(Transactions!I17="",0,Transactions!I17) -> 0.05 | J17: =(H17*G17)*(1-I17) -> 13.509 | K17: Debit Card | L17: Online | M17: =REPLACE(Transactions!M17,1,4,"") -> 12
A18: 104523 | B18: 45319 | C18: 10364 | D18: =PROPER(Transactions!D18) -> Automotive | E18: AU-001 | F18: Motor Oil 5qt | G18: 2 | H18: 19.99 | I18: =IF(Transactions!I18="",0,Transactions!I18) -> 0.2 | J18: =(H18*G18)*(1-I18) -> 31.984 | K18: Credit Card | L18: Online | M18: =REPLACE(Transactions!M18,1,4,"") -> 16
A19: 104855 | B19: 45547 | C19: 48062 | D19: =PROPER(Transactions!D19) -> Furniture | E19: FU-102 | F19: Bookshelf 5-Tier | G19: 2 | H19: 89.99 | I19: =IF(Transactions!I19="",0,Transactions!I19) -> 0 | J19: =(H19*G19)*(1-I19) -> 179.98 | K19: Debit Card | L19: In-Store | M19: =REPLACE(Transactions!M19,1,4,"") -> 6
A20: 105337 | B20: 44814 | C20: 42955 | D20: =PROPER(Transactions!D20) -> Electronics | E20: EL-303 | F20: USB-C Hub | G20: 2 | H20: 34.99 | I20: =IF(Transactions!I20="",0,Transactions!I20) -> 0 | J20: =(H20*G20)*(1-I20) -> 69.98 | K20: Credit Card | L20: Online | M20: =REPLACE(Transactions!M20,1,4,"") -> 13
A21: 105411 | B21: 44805 | C21: 73284 | D21: =PROPER(Transactions!D21) -> Toys | E21: TY-506 | F21: RC Car | G21: 1 | H21: 33.99 | I21: =IF(Transactions!I21="",0,Transactions!I21) -> 0.15 | J21: =(H21*G21)*(1-I21) -> 28.8915 | K21: Debit Card | L21: Online | M21: =REPLACE(Transactions!M21,1,4,"") -> 15
A22: 105767 | B22: 44604 | C22: 15863 | D22: =PROPER(Transactions!D22) -> Grocery | E22: GR-002 | F22: White Bread | G22: 3 | H22: 2.09 | I22: =IF(Transactions!I22="",0,Transactions!I22) -> 0.3 | J22: =(H22*G22)*(1-I22) -> 4.389 | K22: Gift Card | L22: In-Store | M22: =REPLACE(Transactions!M22,1,4,"") -> 20
A23: 105891 | B23: 45425 | C23: 64264 | D23: =PROPER(Transactions!D23) -> Electronics | E23: TV-001 | F23: 4K Smart TV 55" | G23: 1 | H23: 499.99 | I23: =IF(Transactions!I23="",0,Transactions!I23) -> 0 | J23: =(H23*G23)*(1-I23) -> 499.99 | K23: Debit Card | L23: Curbside Pickup | M23: =REPLACE(Transactions!M23,1,4,"") -> 19
A24: 105898 | B24: 45614 | D24: =PROPER(Transactions!D24) -> Electronics | E24: EL-606 | F24: Smart Speaker | G24: 3 | H24: 89.99 | I24: =IF(Transactions!I24="",0,Transactions!I24) -> 0 | J24: =(H24*G24)*(1-I24) -> 269.97 | K24: Credit Card | L24: In-Store | M24: =REPLACE(Transactions!M24,1,4,"") -> 7
A25: 105910 | B25: 45026 | C25: 73703 | D25: =PROPER(Transactions!D25) -> Sports | E25: SP-203 | F25: Water Bottle 32oz | G25: 3 | H25: 11.89 | I25: =IF(Transactions!I25="",0,Transactions!I25) -> 0.3 | J25: =(H25*G25)*(1-I25) -> 24.969 | K25: Debit Card | L25: In-Store | M25: =REPLACE(Transactions!M25,1,4,"") -> 16
A26: 105960 | B26: 45338 | C26: 70702 | D26: =PROPER(Transactions!D26) -> Home & Garden | E26: HG-203 | F26: Scented Candle | G26: 1 | H26: 9.09 | I26: =IF(Transactions!I26="",0,Transactions!I26) -> 0.3 | J26: =(H26*G26)*(1-I26) -> 6.363 | K26: Cash | L26: In-Store | M26: =REPLACE(Transactions!M26,1,4,"") -> 15
A27: 106029 | B27: 45581 | C27: 96438 | D27: =PROPER(Transactions!D27) -> Toys | E27: TY-001 | F27: LEGO City Set | G27: 2 | H27: 37.49 | I27: =IF(Transactions!I27="",0,Transactions!I27) -> 0.25 | J27: =(H27*G27)*(1-I27) -> 56.235 | K27: Credit Card | L27: In-Store | M27: =REPLACE(Transactions!M27,1,4,"") -> 10
A28: 106047 | B28: 44876 | C28: 81600 | D28: =PROPER(Transactions!D28) -> Grocery | E28: GR-006 | F28: Greek Yogurt 32oz | G28: 1 | H28: 4.72 | I28: =IF(Transactions!I28="",0,Transactions!I28) -> 0 | J28: =(H28*G28)*(1-I28) -> 4.72 | K28: Cash | L28: In-Store | M28: =REPLACE(Transactions!M28,1,4,"") -> 7
A29: 106263 | B29: 44902 | C29: 95178 | D29: =PROPER(Transactions!D29) -> Grocery | E29: GR-008 | F29: Canned Tomatoes | G29: 5 | H29: 0.9 | I29: =IF(Transactions!I29="",0,Transactions!I29) -> 0.3 | J29: =(H29*G29)*(1-I29) -> 3.15 | K29: Mobile Pay | L29: In-Store | M29: =REPLACE(Transactions!M29,1,4,"") -> 14
A30: 106543 | B30: 45204 | C30: 88674 | D30: =PROPER(Transactions!D30) -> Automotive | E30: AU-203 | F30: Windshield Washer Fluid | G30: 1 | H30: 3.99 | I30: =IF(Transactions!I30="",0,Transactions!I30) -> 0.2 | J30: =(H30*G30)*(1-I30) -> 3.192 | K30: Debit Card | L30: In-Store | M30: =REPLACE(Transactions!M30,1,4,"") -> 9
A31: 106587 | B31: 45594 | C31: 94688 | D31: =PROPER(Transactions!D31) -> Clothing | E31: CL-506 | F31: Yoga Pants | G31: 4 | H31: 27.99 | I31: =IF(Transactions!I31="",0,Transactions!I31) -> 0 | J31: =(H31*G31)*(1-I31) -> 111.96 | K31: Credit Card | L31: In-Store | M31: =REPLACE(Transactions!M31,1,4,"") -> 1
A32: 106747 | B32: 45229 | C32: 22687 | D32: =PROPER(Transactions!D32) -> Automotive | E32: AU-001 | F32: Motor Oil 5qt | G32: 2 | H32: 19.99 | I32: =IF(Transactions!I32="",0,Transactions!I32) -> 0.2 | J32: =(H32*G32)*(1-I32) -> 31.984 | K32: Cash | L32: Online | M32: =REPLACE(Transactions!M32,1,4,"") -> 20
A33: 106802 | B33: 45075 | C33: 54297 | D33: =PROPER(Transactions!D33) -> Toys | E33: TY-304 | F33: Board Game | G33: 1 | H33: 28.49 | I33: =IF(Transactions!I33="",0,Transactions!I33) -> 0.05 | J33: =(H33*G33)*(1-I33) -> 27.0655 | K33: Credit Card | L33: Online | M33: =REPLACE(Transactions!M33,1,4,"") -> 10
A34: 106949 | B34: 45526 | C34: 77873 | D34: =PROPER(Transactions!D34) -> Sports | E34: SP-001 | F34: Yoga Mat | G34: 2 | H34: 22.99 | I34: =IF(Transactions!I34="",0,Transactions!I34) -> 0 | J34: =(H34*G34)*(1-I34) -> 45.98 | K34: Check | L34: Online | M34: =REPLACE(Transactions!M34,1,4,"") -> 8
A35: 106959 | B35: 45625 | C35: 17057 | D35: =PROPER(Transactions!D35) -> Pharmacy | E35: PH-405 | F35: Hand Sanitizer 8oz | G35: 2 | H35: 3.39 | I35: =IF(Transactions!I35="",0,Transactions!I35) -> 0.15 | J35: =(H35*G35)*(1-I35) -> 5.763 | K35: EBT | L35: Online | M35: =REPLACE(Transactions!M35,1,4,"") -> 17
A36: 107239 | B36: 44834 | C36: 29478 | D36: =PROPER(Transactions!D36) -> Grocery | E36: GR-002 | F36: White Bread | G36: 1 | H36: 2.09 | I36: =IF(Transactions!I36="",0,Transactions!I36) -> 0.3 | J36: =(H36*G36)*(1-I36) -> 1.463 | K36: Cash | L36: In-Store | M36: =REPLACE(Transactions!M36,1,4,"") -> 6
... A57: 110649 | B57: 45296 | C57: 87204 | D57: =PROPER(Transactions!D57) -> Electronics | E57: TV-001 | F57: 4K Smart TV 55" | G57: 1 | H57: 374.99 | I57: =IF(Transactions!I57="",0,Transactions!I57) -> 0.25 | J57: =(H57*G57)*(1-I57) -> 281.2425 | K57: Mobile Pay | L57: In-Store | M57: =REPLACE(Transactions!M57,1,4,"") -> 10
A58: 110666 | B58: 45167 | D58: =PROPER(Transactions!D58) -> Automotive | E58: AU-102 | F58: Car Air Freshener | G58: 2 | H58: 3.49 | I58: =IF(Transactions!I58="",0,Transactions!I58) -> 0 | J58: =(H58*G58)*(1-I58) -> 6.98 | K58: Cash | L58: In-Store | M58: =REPLACE(Transactions!M58,1,4,"") -> 2
A59: 110743 | B59: 44901 | C59: 16675 | D59: =PROPER(Transactions!D59) -> Beauty | E59: BE-304 | F59: Lip Balm 3pk | G59: 1 | H59: 4.24 | I59: =IF(Transactions!I59="",0,Transactions!I59) -> 0.15 | J59: =(H59*G59)*(1-I59) -> 3.604 | K59: Cash | L59: In-Store | M59: =REPLACE(Transactions!M59,1,4,"") -> 18
A60: 111256 | B60: 44659 | C60: 15018 | D60: =PROPER(Transactions!D60) -> Grocery | E60: GR-004 | F60: Bagged Salad Mix | G60: 1 | H60: 3.79 | I60: =IF(Transactions!I60="",0,Transactions!I60) -> 0 | J60: =(H60*G60)*(1-I60) -> 3.79 | K60: Credit Card | L60: In-Store | M60: =REPLACE(Transactions!M60,1,4,"") -> 18
A61: 111480 | B61: 44578 | D61: =PROPER(Transactions!D61) -> Clothing | E61: CL-607 | F61: Dress Socks 6pk | G61: 2 | H61: 6.99 | I61: =IF(Transactions!I61="",0,Transactions!I61) -> 0.3 | J61: =(H61*G61)*(1-I61) -> 9.786 | K61: Debit Card | L61: In-Store | M61: =REPLACE(Transactions!M61,1,4,"") -> 6
A62: 111503 | B62: 45305 | C62: 66196 | D62: =PROPER(Transactions!D62) -> Pharmacy | E62: PH-102 | F62: Vitamin D 100ct | G62: 1 | H62: 9.74 | I62: =IF(Transactions!I62="",0,Transactions!I62) -> 0.25 | J62: =(H62*G62)*(1-I62) -> 7.305 | K62: Credit Card | L62: In-Store | M62: =REPLACE(Transactions!M62,1,4,"") -> 5
A63: 111807 | B63: 44618 | D63: =PROPER(Transactions!D63) -> Home & Garden | E63: HG-304 | F63: Picture Frame 8x10 | G63: 2 | H63: 6.79 | I63: =IF(Transactions!I63="",0,Transactions!I63) -> 0.15 | J63: =(H63*G63)*(1-I63) -> 11.543 | K63: Cash | L63: In-Store | M63: =REPLACE(Transactions!M63,1,4,"") -> 13
A64: 111972 | B64: 45387 | C64: 67694 | D64: =PROPER(Transactions!D64) -> Beauty | E64: BE-405 | F64: Body Lotion 16oz | G64: 2 | H64: 7.99 | I64: =IF(Transactions!I64="",0,Transactions!I64) -> 0 | J64: =(H64*G64)*(1-I64) -> 15.98 | K64: Credit Card | L64: In-Store | M64: =REPLACE(Transactions!M64,1,4,"") -> 15
A65: 112088 | B65: 45103 | C65: 39411 | D65: =PROPER(Transactions!D65) -> Clothing | E65: CL-203 | F65: Kids Hoodie | G65: 3 | H65: 16.09 | I65: =IF(Transactions!I65="",0,Transactions!I65) -> 0.3 | J65: =(H65*G65)*(1-I65) -> 33.789 | K65: Cash | L65: In-Store | M65: =REPLACE(Transactions!M65,1,4,"")
A66: 112439 | B66: 44859 | C66: 51377 | D66: =PROPER(Transactions!D66) -> Beauty | E66: BE-304 | F66: Lip Balm 3pk | G66: 4 | H66: 3.49 | I66: =IF(Transactions!I66="",0,Transactions!I66) -> 0.3 | J66: =(H66*G66)*(1-I66) -> 9.772 | K66: Debit Card | L66: Online | M66: =REPLACE(Transactions!M66,1,4,"") -> 19
A67: 112458 | B67: 45057 | C67: 15965 | D67: =PROPER(Transactions!D67) -> Toys | E67: TY-506 | F67: RC Car | G67: 4 | H67: 39.99 | I67: =IF(Transactions!I67="",0,Transactions!I67) -> 0 | J67: =(H67*G67)*(1-I67) -> 159.96 | K67: EBT | L67: In-Store | M67: =REPLACE(Transactions!M67,1,4,"") -> 10
A68: 112714 | B68: 44744 | C68: 43443 | D68: =PROPER(Transactions!D68) -> Automotive | E68: AU-001 | F68: Motor Oil 5qt | G68: 1 | H68: 24.99 | I68: =IF(Transactions!I68="",0,Transactions!I68) -> 0 | J68: =(H68*G68)*(1-I68) -> 24.99 | K68: Credit Card | L68: In-Store | M68: =REPLACE(Transactions!M68,1,4,"") -> 19
A69: 112715 | B69: 45578 | C69: 44039 | D69: =PROPER(Transactions!D69) -> Beauty | E69: BE-102 | F69: Face Moisturizer | G69: 1 | H69: 14.99 | I69: =IF(Transactions!I69="",0,Transactions!I69) -> 0 | J69: =(H69*G69)*(1-I69) -> 14.99 | K69: Check | L69: Curbside Pickup | M69: =REPLACE(Transactions!M69,1,4,"") -> 16
A70: 112778 | B70: 45543 | C70: 34879 | D70: =PROPER(Transactions!D70) -> Home & Garden | E70: HG-405 | F70: Storage Bins 3pk | G70: 2 | H70: 13.59 | I70: =IF(Transactions!I70="",0,Transactions!I70) -> 0.2 | J70: =(H70*G70)*(1-I70) -> 21.744 | K70: Gift Card | L70: Online | M70: =REPLACE(Transactions!M70,1,4,"") -> 7
A71: 112940 | B71: 44752 | C71: 83339 | D71: =PROPER(Transactions!D71) -> Clothing | E71: CL-506 | F71: Yoga Pants | G71: 4 | H71: 23.79 | I71: =IF(Transactions!I71="",0,Transactions!I71) -> 0.15 | J71: =(H71*G71)*(1-I71) -> 80.886 | K71: Credit Card | L71: In-Store | M71: =REPLACE(Transactions!M71,1,4,"") -> 16
A72: 113121 | B72: 45431 | C72: 86078 | D72: =PROPER(Transactions!D72) -> Electronics | E72: EL-102 | F72: Bluetooth Headphones | G72: 1 | H72: 79.99 | I72: =IF(Transactions!I72="",0,Transactions!I72) -> 0 | J72: =(H72*G72)*(1-I72) -> 79.99 | K72: Credit Card | L72: Online | M72: =REPLACE(Transactions!M72,1,4,"") -> 15
A73: 113173 | B73: 45253 | C73: 29832 | D73: =PROPER(Transactions!D73) -> Sports | E73: SP-304 | F73: Resistance Bands | G73: 2 | H73: 9.74 | I73: =IF(Transactions!I73="",0,Transactions!I73) -> 0.25 | J73: =(H73*G73)*(1-I73) -> 14.61 | K73: Debit Card | L73: In-Store | M73: =REPLACE(Transactions!M73,1,4,"") -> 20
A74: 113177 | B74: 45358 | C74: 29893 | D74: =PROPER(Transactions!D74) -> Furniture | E74: FU-203 | F74: Desk Lamp | G74: 5 | H74: 20.99 | I74: =IF(Transactions!I74="",0,Transactions!I74) -> 0.25 | J74: =(H74*G74)*(1-I74) -> 78.7125 | K74: EBT | L74: In-Store | M74: =REPLACE(Transactions!M74,1,4,"") -> 11
A75: 113499 | B75: 44699 | D75: =PROPER(Transactions!D75) -> Furniture | E75: FU-203 | F75: Desk Lamp | G75: 3 | H75: 27.99 | I75: =IF(Transactions!I75="",0,Transactions!I75) -> 0 | J75: =(H75*G75)*(1-I75) -> 83.97 | K75: Credit Card | L75: Curbside Pickup | M75: =REPLACE(Transactions!M75,1,4,"")
A76: 113522 | B76: 44773 | C76: 53050 | D76: =PROPER(Transactions!D76) -> Toys | E76: TY-506 | F76: RC Car | G76: 1 | H76: 39.99 | I76: =IF(Transactions!I76="",0,Transactions!I76) -> 0 | J76: =(H76*G76)*(1-I76) -> 39.99 | K76: Gift Card | L76: In-Store | M76: =REPLACE(Transactions!M76,1,4,"") -> 3
A77: 113765 | B77: 44715 | C77: 73916 | D77: =PROPER(Transactions!D77) -> Home & Garden | E77: HG-506 | F77: Throw Pillow | G77: 1 | H77: 14.99 | I77: =IF(Transactions!I77="",0,Transactions!I77) -> 0.25 | J77: =(H77*G77)*(1-I77) -> 11.2425 | K77: Debit Card | L77: In-Store | M77: =REPLACE(Transactions!M77,1,4,"") -> 17
A78: 114210 | B78: 45348 | C78: 42550 | D78: =PROPER(Transactions!D78) -> Electronics | E78: EL-102 | F78: Bluetooth Headphones | G78: 1 | H78: 79.99 | I78: =IF(Transactions!I78="",0,Transactions!I78) -> 0 | J78: =(H78*G78)*(1-I78) -> 79.99 | K78: Credit Card | L78: In-Store | M78: =REPLACE(Transactions!M78,1,4,"") -> 11
A79: 114270 | B79: 45331 | D79: =PROPER(Transactions!D79) -> Grocery | E79: GR-004 | F79: Bagged Salad Mix | G79: 1 | H79: 3.79 | I79: =IF(Transactions!I79="",0,Transactions!I79) -> 0 | J79: =(H79*G79)*(1-I79) -> 3.79 | K79: Cash | L79: In-Store | M79: =REPLACE(Transactions!M79,1,4,"") -> 5
A80: 114717 | B80: 44835 | C80: 82298 | D80: =PROPER(Transactions!D80) -> Clothing | E80: CL-001 | F80: Men's Jeans | G80: 4 | H80: 33.24 | I80: =IF(Transactions!I80="",0,Transactions!I80) -> 0.05 | J80: =(H80*G80)*(1-I80) -> 126.312 | K80: Gift Card | L80: Curbside Pickup | M80: =REPLACE(Transactions!M80,1,4,"") -> 13
A81: 114743 | B81: 45627 | C81: 96886 | D81: =PROPER(Transactions!D81) -> Toys | E81: TY-203 | F81: Nerf Gun | G81: 2 | H81: 23.74 | I81: =IF(Transactions!I81="",0,Transactions!I81) -> 0.05 | J81: =(H81*G81)*(1-I81) -> 45.106 | K81: Credit Card | L81: In-Store | M81: =REPLACE(Transactions!M81,1,4,"") -> 1
A82: 114834 | B82: 44953 | C82: 17772 | D82: =PROPER(Transactions!D82) -> Home & Garden | E82: HG-102 | F82: Garden Hose 50ft | G82: 4 | H82: 26.99 | I82: =IF(Transactions!I82="",0,Transactions!I82) -> 0.1 | J82: =(H82*G82)*(1-I82) -> 97.164 | K82: Mobile Pay | L82: In-Store | M82: =REPLACE(Transactions!M82,1,4,"") -> 19
A83: 114868 | B83: 45348 | C83: 93946 | D83: =PROPER(Transactions!D83) -> Electronics | E83: EL-707 | F83: Tablet 10" | G83: 1 | H83: 329.99 | I83: =IF(Transactions!I83="",0,Transactions!I83) -> 0 | J83: =(H83*G83)*(1-I83) -> 329.99 | K83: Credit Card | L83: In-Store | M83: =REPLACE(Transactions!M83,1,4,"") -> 18
A84: 114930 | B84: 44854 | C84: 42668 | D84: =PROPER(Transactions!D84) -> Home & Garden | E84: HG-405 | F84: Storage Bins 3pk | G84: 1 | H84: 16.99 | I84: =IF(Transactions!I84="",0,Transactions!I84) -> 0 | J84: =(H84*G84)*(1-I84) -> 16.99 | K84: Credit Card | L84: Online | M84: =REPLACE(Transactions!M84,1,4,"") -> 8
A85: 115017 | B85: 44660 | C85: 31218 | D85: =PROPER(Transactions!D85) -> Electronics | E85: EL-606 | F85: Smart Speaker | G85: 5 | H85: 85.49 | I85: =IF(Transactions!I85="",0,Transactions!I85) -> 0.05 | J85: =(H85*G85)*(1-I85) -> 406.0775 | K85: Cash | L85: In-Store | M85: =REPLACE(Transactions!M85,1,4,"") -> 9
A86: 115166 | B86: 44810 | C86: 31680 | D86: =PROPER(Transactions!D86) -> Furniture | E86: FU-304 | F86: Storage Ottoman | G86: 1 | H86: 52.24 | I86: =IF(Transactions!I86="",0,Transactions!I86) -> 0.05 | J86: =(H86*G86)*(1-I86) -> 49.628 | K86: Credit Card | L86: Online | M86: =REPLACE(Transactions!M86,1,4,"") -> 12
A87: 115330 | B87: 44615 | C87: 74764 | D87: =PROPER(Transactions!D87) -> Furniture | E87: FU-102 | F87: Bookshelf 5-Tier | G87: 1 | H87: 67.49 | I87: =IF(Transactions!I87="",0,Transactions!I87) -> 0.25 | J87: =(H87*G87)*(1-I87) -> 50.6175 | K87: Debit Card | L87: In-Store | M87: =REPLACE(Transactions!M87,1,4,"") -> 8
A88: 115577 | B88: 44714 | C88: 33437 | D88: =PROPER(Transactions!D88) -> Sports | E88: SP-506 | F88: Foam Roller | G88: 1 | H88: 15.99 | I88: =IF(Transactions!I88="",0,Transactions!I88) -> 0.2 | J88: =(H88*G88)*(1-I88) -> 12.792 | K88: Debit Card | L88: In-Store | M88: =REPLACE(Transactions!M88,1,4,"") -> 9
A89: 115659 | B89: 45396 | C89: 85378 | D89: =PROPER(Transactions!D89) -> Home & Garden | E89: HG-607 | F89: Laundry Detergent | G89: 1 | H89: 13.49 | I89: =IF(Transactions!I89="",0,Transactions!I89) -> 0 | J89: =(H89*G89)*(1-I89) -> 13.49 | K89: Cash | L89: In-Store | M89: =REPLACE(Transactions!M89,1,4,"") -> 19
A90: 115664 | B90: 45637 | C90: 18693 | D90: =PROPER(Transactions!D90) -> Electronics | E90: EL-808 | F90: Gaming Controller | G90: 1 | H90: 59.99 | I90: =IF(Transactions!I90="",0,Transactions!I90) -> 0 | J90: =(H90*G90)*(1-I90) -> 59.99 | K90: Debit Card | L90: In-Store | M90: =REPLACE(Transactions!M90,1,4,"") -> 4
A91: 115775 | B91: 45523 | C91: 65009 | D91: =PROPER(Transactions!D91) -> Furniture | E91: FU-203 | F91: Desk Lamp | G91: 2 | H91: 27.99 | I91: =IF(Transactions!I91="",0,Transactions!I91) -> 0 | J91: =(H91*G91)*(1-I91) -> 55.98 | K91: Credit Card | L91: In-Store | M91: =REPLACE(Transactions!M91,1,4,"") -> 16
... A96: 117452 | B96: 44756 | C96: 73624 | D96: =PROPER(Transactions!D96) -> Home & Garden | E96: HG-607 | F96: Laundry Detergent | G96: 3 | H96: 9.44 | I96: =IF(Transactions!I96="",0,Transactions!I96) -> 0.3 | J96: =(H96*G96)*(1-I96) -> 19.824 | K96: Credit Card | L96: Online | M96: =REPLACE(Transactions!M96,1,4,"") -> 14
A97: 117463 | B97: 45267 | D97: =PROPER(Transactions!D97) -> Home & Garden | E97: HG-607 | F97: Laundry Detergent | G97: 1 | H97: 12.82 | I97: =IF(Transactions!I97="",0,Transactions!I97) -> 0.05 | J97: =(H97*G97)*(1-I97) -> 12.179 | K97: Check | L97: In-Store | M97: =REPLACE(Transactions!M97,1,4,"") -> 17
A98: 117526 | B98: 44684 | C98: 72147 | D98: =PROPER(Transactions!D98) -> Furniture | E98: FU-001 | F98: Folding Chair | G98: 4 | H98: 34.99 | I98: =IF(Transactions!I98="",0,Transactions!I98) -> 0 | J98: =(H98*G98)*(1-I98) -> 139.96 | K98: Debit Card | L98: In-Store | M98: =REPLACE(Transactions!M98,1,4,"") -> 16
A99: 117538 | B99: 45651 | C99: 12246 | D99: =PROPER(Transactions!D99) -> Pharmacy | E99: PH-001 | F99: Ibuprofen 200ct | G99: 2 | H99: 6.99 | I99: =IF(Transactions!I99="",0,Transactions!I99) -> 0.3 | J99: =(H99*G99)*(1-I99) -> 9.786 | K99: Mobile Pay | L99: In-Store | M99: =REPLACE(Transactions!M99,1,4,"") -> 8
A100: 117658 | B100: 44969 | C100: 62952 | D100: =PROPER(Transactions!D100) -> Automotive | E100: AU-405 | F100: Jumper Cables | G100: 3 | H100: 29.99 | I100: =IF(Transactions!I100="",0,Transactions!I100) -> 0 | J100: =(H100*G100)*(1-I100) -> 89.97 | K100: Credit Card | L100: In-Store | M100: =REPLACE(Transactions!M100,1,4,"") -> 7
A101: 117819 | B101: 45504 | C101: 78920 | D101: =PROPER(Transactions!D101) -> Home & Garden | E101: HG-102 | F101: Garden Hose 50ft | G101: 4 | H101: 25.49 | I101: =IF(Transactions!I101="",0,Transactions!I101) -> 0.15 | J101: =(H101*G101)*(1-I101) -> 86.666 | K101: Mobile Pay | L101: Online | M101: =REPLACE(Transactions!M101,1,4,"") -> 16
A102: 118025 | B102: 45570 | D102: =PROPER(Transactions!D102) -> Automotive | E102: AU-405 | F102: Jumper Cables | G102: 2 | H102: 20.99 | I102: =IF(Transactions!I102="",0,Transactions!I102) -> 0.3 | J102: =(H102*G102)*(1-I102) -> 29.386 | K102: Cash | L102: In-Store | M102: =REPLACE(Transactions!M102,1,4,"") -> 17
A103: 118632 | B103: 44805 | C103: 10022 | D103: =PROPER(Transactions!D103) -> Pharmacy | E103: PH-304 | F103: Bandage Assortment | G103: 3 | H103: 4.49 | I103: =IF(Transactions!I103="",0,Transactions!I103) -> 0.25 | J103: =(H103*G103)*(1-I103) -> 10.1025 | K103: Debit Card | L103: In-Store | M103: =REPLACE(Transactions!M103,1,4,"") -> 4
A104: 119232 | B104: 44602 | C104: 36778 | D104: =PROPER(Transactions!D104) -> Toys | E104: TY-203 | F104: Nerf Gun | G104: 2 | H104: 19.99 | I104: =IF(Transactions!I104="",0,Transactions!I104) -> 0.2 | J104: =(H104*G104)*(1-I104) -> 31.984 | K104: Mobile Pay | L104: In-Store | M104: =REPLACE(Transactions!M104,1,4,"") -> 8
A105: 119393 | B105: 45008 | C105: 88352 | D105: =PROPER(Transactions!D105) -> Sports | E105: SP-203 | F105: Water Bottle 32oz | G105: 2 | H105: 16.99 | I105: =IF(Transactions!I105="",0,Transactions!I105) -> 0 | J105: =(H105*G105)*(1-I105) -> 33.98 | K105: Debit Card | L105: Curbside Pickup | M105: =REPLACE(Transactions!M105,1,4,"") -> 18
A106: 119460 | B106: 44880 | D106: =PROPER(Transactions!D106) -> Automotive | E106: AU-304 | F106: Car Phone Mount | G106: 5 | H106: 12.74 | I106: =IF(Transactions!I106="",0,Transactions!I106) -> 0.15 | J106: =(H106*G106)*(1-I106) -> 54.145 | K106: Credit Card | L106: In-Store | M106: =REPLACE(Transactions!M106,1,4,"") -> 18
A107: 119629 | B107: 44992 | C107: 68002 | D107: =PROPER(Transactions!D107) -> Toys | E107: TY-506 | F107: RC Car | G107: 1 | H107: 37.99 | I107: =IF(Transactions!I107="",0,Transactions!I107) -> 0 | J107: =(H107*G107)*(1-I107) -> 37.99 | K107: Cash | L107: Curbside Pickup | M107: =REPLACE(Transactions!M107,1,4,"") -> 19
A108: 119661 | B108: 45490 | C108: 95598 | D108: =PROPER(Transactions!D108) -> Toys | E108: TY-304 | F108: Board Game | G108: 1 | H108: 28.49 | I108: =IF(Transactions!I108="",0,Transactions!I108) -> 0.05 | J108: =(H108*G108)*(1-I108) -> 27.0655 | K108: Debit Card | L108: In-Store | M108: =REPLACE(Transactions!M108,1,4,"") -> 17
A109: 119746 | B109: 45424 | C109: 10979 | D109: =PROPER(Transactions!D109) -> Toys | E109: TY-304 | F109: Board Game | G109: 4 | H109: 29.99 | I109: =IF(Transactions!I109="",0,Transactions!I109) -> 0 | J109: =(H109*G109)*(1-I109) -> 119.96 | K109: Debit Card | L109: In-Store | M109: =REPLACE(Transactions!M109,1,4,"") -> 6
A110: 119771 | B110: 44714 | C110: 63538 | D110: =PROPER(Transactions!D110) -> Home & Garden | E110: HG-506 | F110: Throw Pillow | G110: 2 | H110: 15.99 | I110: =IF(Transactions!I110="",0,Transactions!I110) -> 0.2 | J110: =(H110*G110)*(1-I110) -> 25.584 | K110: Debit Card | L110: Curbside Pickup | M110: =REPLACE(Transactions!M110,1,4,"") -> 20
A111: 120121 | B111: 45475 | C111: 15194 | D111: =PROPER(Transactions!D111) -> Automotive | E111: AU-203 | F111: Windshield Washer Fluid | G111: 1 | H111: 3.99 | I111: =IF(Transactions!I111="",0,Transactions!I111) -> 0.2 | J111: =(H111*G111)*(1-I111) -> 3.192 | K111: Credit Card | L111: In-Store | M111: =REPLACE(Transactions!M111,1,4,"") -> 11
A112: 120203 | B112: 44772 | C112: 11904 | D112: =PROPER(Transactions!D112) -> Clothing | E112: CL-203 | F112: Kids Hoodie | G112: 2 | H112: 16.09 | I112: =IF(Transactions!I112="",0,Transactions!I112) -> 0.3 | J112: =(H112*G112)*(1-I112) -> 22.526 | K112: Credit Card | L112: In-Store | M112: =REPLACE(Transactions!M112,1,4,"") -> 15
A113: 120525 | B113: 45517 | C113: 60160 | D113: =PROPER(Transactions!D113) -> Home & Garden | E113: HG-001 | F113: Potting Soil 20qt | G113: 2 | H113: 7.19 | I113: =IF(Transactions!I113="",0,Transactions!I113) -> 0.2 | J113: =(H113*G113)*(1-I113) -> 11.504 | K113: Debit Card | L113: In-Store | M113: =REPLACE(Transactions!M113,1,4,"") -> 7
A114: 120937 | B114: 45455 | C114: 38872 | D114: =PROPER(Transactions!D114) -> Clothing | E114: CL-102 | F114: Women's T-Shirt | G114: 4 | H114: 9.09 | I114: =IF(Transactions!I114="",0,Transactions!I114) -> 0.3 | J114: =(H114*G114)*(1-I114) -> 25.452 | K114: Debit Card | L114: In-Store | M114: =REPLACE(Transactions!M114,1,4,"") -> 17
A115: 121265 | B115: 45136 | C115: 35144 | D115: =PROPER(Transactions!D115) -> Clothing | E115: CL-405 | F115: Winter Jacket | G115: 2 | H115: 89.99 | I115: =IF(Transactions!I115="",0,Transactions!I115) -> 0 | J115: =(H115*G115)*(1-I115) -> 179.98 | K115: Check | L115: Curbside Pickup | M115: =REPLACE(Transactions!M115,1,4,"") -> 4
A116: 121283 | B116: 45255 | C116: 96636 | D116: =PROPER(Transactions!D116) -> Furniture | E116: FU-304 | F116: Storage Ottoman | G116: 4 | H116: 54.99 | I116: =IF(Transactions!I116="",0,Transactions!I116) -> 0 | J116: =(H116*G116)*(1-I116) -> 219.96 | K116: Credit Card | L116: In-Store | M116: =REPLACE(Transactions!M116,1,4,"") -> 9
A117: 121590 | B117: 44627 | C117: 40999 | D117: =PROPER(Transactions!D117) -> Home & Garden | E117: HG-405 | F117: Storage Bins 3pk | G117: 2 | H117: 13.59 | I117: =IF(Transactions!I117="",0,Transactions!I117) -> 0.2 | J117: =(H117*G117)*(1-I117) -> 21.744 | K117: Credit Card | L117: In-Store | M117: =REPLACE(Transactions!M117,1,4,"") -> 3
A118: 121734 | B118: 45114 | C118: 28564 | D118: =PROPER(Transactions!D118) -> Furniture | E118: FU-304 | F118: Storage Ottoman | G118: 3 | H118: 38.49 | I118: =IF(Transactions!I118="",0,Transactions!I118) -> 0.3 | J118: =(H118*G118)*(1-I118) -> 80.829 | K118: Credit Card | L118: In-Store | M118: =REPLACE(Transactions!M118,1,4,"") -> 17
... A166: 130246 | B166: 45617 | C166: 73511 | D166: =PROPER(Transactions!D166) -> Clothing | E166: CL-506 | F166: Yoga Pants | G166: 4 | H166: 19.59 | I166: =IF(Transactions!I166="",0,Transactions!I166) -> 0.3 | J166: =(H166*G166)*(1-I166) -> 54.852 | K166: EBT | L166: Online | M166: =REPLACE(Transactions!M166,1,4,"") -> 6
A167: 130454 | B167: 45091 | D167: =PROPER(Transactions!D167) -> Grocery | E167: GR-004 | F167: Bagged Salad Mix | G167: 1 | H167: 2.84 | I167: =IF(Transactions!I167="",0,Transactions!I167) -> 0.25 | J167: =(H167*G167)*(1-I167) -> 2.13 | K167: Mobile Pay | L167: Online | M167: =REPLACE(Transactions!M167,1,4,"") -> 9
A168: 130688 | B168: 45006 | C168: 84301 | D168: =PROPER(Transactions!D168) -> Home & Garden | E168: HG-304 | F168: Picture Frame 8x10 | G168: 5 | H168: 7.99 | I168: =IF(Transactions!I168="",0,Transactions!I168) -> 0 | J168: =(H168*G168)*(1-I168) -> 39.95 | K168: Debit Card | L168: In-Store | M168: =REPLACE(Transactions!M168,1,4,"") -> 8
A169: 130959 | B169: 44801 | D169: =PROPER(Transactions!D169) -> Clothing | E169: CL-405 | F169: Winter Jacket | G169: 1 | H169: 76.49 | I169: =IF(Transactions!I169="",0,Transactions!I169) -> 0.15 | J169: =(H169*G169)*(1-I169) -> 65.0165 | K169: Credit Card | L169: In-Store | M169: =REPLACE(Transactions!M169,1,4,"") -> 17
A170: 130971 | B170: 45200 | D170: =PROPER(Transactions!D170) -> Sports | E170: SP-405 | F170: Jump Rope | G170: 5 | H170: 8.99 | I170: =IF(Transactions!I170="",0,Transactions!I170) -> 0 | J170: =(H170*G170)*(1-I170) -> 44.95 | K170: Mobile Pay | L170: In-Store | M170: =REPLACE(Transactions!M170,1,4,"") -> 16
A171: 131544 | B171: 45035 | C171: 31891 | D171: =PROPER(Transactions!D171) -> Pharmacy | E171: PH-001 | F171: Ibuprofen 200ct | G171: 5 | H171: 8.49 | I171: =IF(Transactions!I171="",0,Transactions!I171) -> 0.15 | J171: =(H171*G171)*(1-I171) -> 36.0825 | K171: Cash | L171: Curbside Pickup | M171: =REPLACE(Transactions!M171,1,4,"")
...
